{
  "updated_at_utc": "2026-05-29T20:04:51.020529+00:00",
  "date": "2026-05-29",
  "overall_status": "connected",
  "account_status": "connected",
  "net_liquidation": 1015527.23,
  "net_liquidation_value": 1015527.23,
  "portfolio_value": 1015527.23,
  "equity": 1015527.23,
  "source": "alpaca_account_equity",
  "selected_assets": [
    "SMH",
    "XLK"
  ],
  "target_weights": {
    "SGOV": 0.6737771073788985,
    "XLK": 0.19695195843882662,
    "SMH": 0.1292709341822748
  },
  "submitted_order_count": 2,
  "paper_base_url": "https://paper-api.alpaca.markets"
}